odoo/addons/delivery_gls_asm/README.rst
odoo/addons/delivery_gls_asm/__init__.py
odoo/addons/delivery_gls_asm/__manifest__.py
odoo/addons/delivery_gls_asm/api/gls_asm_api.wsdl
odoo/addons/delivery_gls_asm/data/delivery_asm_data.xml
odoo/addons/delivery_gls_asm/i18n/ca.po
odoo/addons/delivery_gls_asm/i18n/delivery_gls_asm.pot
odoo/addons/delivery_gls_asm/i18n/es.po
odoo/addons/delivery_gls_asm/models/__init__.py
odoo/addons/delivery_gls_asm/models/delivery_carrier.py
odoo/addons/delivery_gls_asm/models/gls_asm_master_data.py
odoo/addons/delivery_gls_asm/models/gls_asm_request.py
odoo/addons/delivery_gls_asm/models/stock_picking.py
odoo/addons/delivery_gls_asm/readme/CONFIGURE.md
odoo/addons/delivery_gls_asm/readme/CONTRIBUTORS.md
odoo/addons/delivery_gls_asm/readme/DESCRIPTION.md
odoo/addons/delivery_gls_asm/readme/INSTALL.md
odoo/addons/delivery_gls_asm/readme/ROADMAP.md
odoo/addons/delivery_gls_asm/readme/USAGE.md
odoo/addons/delivery_gls_asm/security/ir.model.access.csv
odoo/addons/delivery_gls_asm/static/description/icon.png
odoo/addons/delivery_gls_asm/static/description/icon.svg
odoo/addons/delivery_gls_asm/static/description/index.html
odoo/addons/delivery_gls_asm/tests/__init__.py
odoo/addons/delivery_gls_asm/tests/test_delivery_gls_asm.py
odoo/addons/delivery_gls_asm/views/delivery_asm_view.xml
odoo/addons/delivery_gls_asm/views/gls_asm_manifest_template.xml
odoo/addons/delivery_gls_asm/views/stock_picking_views.xml
odoo/addons/delivery_gls_asm/wizard/__init__.py
odoo/addons/delivery_gls_asm/wizard/gls_asm_manifest_wizard.py
odoo/addons/delivery_gls_asm/wizard/gls_asm_manifest_wizard_views.xml
odoo_addon_delivery_gls_asm-18.0.1.0.4.1.dist-info/METADATA
odoo_addon_delivery_gls_asm-18.0.1.0.4.1.dist-info/WHEEL
odoo_addon_delivery_gls_asm-18.0.1.0.4.1.dist-info/top_level.txt
odoo_addon_delivery_gls_asm-18.0.1.0.4.1.dist-info/RECORD
